Metadata-Version: 2.1
Name: Mensajes-Luis_David
Version: 6.0
Summary: Un paquete para saludar y despedir
Home-page: https://noesmidireccion.com
Author: Luis David López-Roberts Luzón
Author-email: luisdavid.lrlmp@gmail.com
Classifier: Environment :: Console
Classifier: Intended Audience :: Developers
Classifier: License :: OSI Approved :: MIT License
Classifier: Operating System :: OS Independent
Classifier: Programming Language :: Python
Classifier: Programming Language :: Python :: 3.12
Classifier: Topic :: Utilities
License-File: LICENSE
Requires-Dist: numpy>=2.1.3
Requires-Dist: doc8
Requires-Dist: flake8
Requires-Dist: flake8-import-order
Requires-Dist: pathspec
Requires-Dist: pytest
Requires-Dist: pyyaml
Requires-Dist: sphinx
